LICENSE
MANIFEST.in
README.md
pyproject.toml
requirements_python39.txt
neural_de/__init__.py
neural_de/main.py
neural_de/external/__init__.py
neural_de/external/_checksums/checksums.json
neural_de/external/_repositories/external_models_list.yaml
neural_de/external/derain/__init__.py
neural_de/external/derain/blocks.py
neural_de/external/maxim_tf/__init__.py
neural_de/external/maxim_tf/create_maxim_model.py
neural_de/external/maxim_tf/maxim/__init__.py
neural_de/external/maxim_tf/maxim/configs.py
neural_de/external/maxim_tf/maxim/layers.py
neural_de/external/maxim_tf/maxim/maxim.py
neural_de/external/maxim_tf/maxim/blocks/__init__.py
neural_de/external/maxim_tf/maxim/blocks/attentions.py
neural_de/external/maxim_tf/maxim/blocks/block_gating.py
neural_de/external/maxim_tf/maxim/blocks/bottleneck.py
neural_de/external/maxim_tf/maxim/blocks/grid_gating.py
neural_de/external/maxim_tf/maxim/blocks/misc_gating.py
neural_de/external/maxim_tf/maxim/blocks/others.py
neural_de/external/maxim_tf/maxim/blocks/unet.py
neural_de/external/nplie/__init__.py
neural_de/external/nplie/nplie.py
neural_de/external/prenet/__init__.py
neural_de/external/prenet/networks.py
neural_de/transformations/__init__.py
neural_de/transformations/brightness_enhancer.py
neural_de/transformations/centered_zoom.py
neural_de/transformations/de_rain_enhancer.py
neural_de/transformations/de_snow_enhancer.py
neural_de/transformations/kernel_deblurring_enhancer.py
neural_de/transformations/night_image_enhancer.py
neural_de/transformations/resolution_enhancer.py
neural_de/transformations/transformation.py
neural_de/transformations/transformation_pipeline.py
neural_de/transformations/diffusion/__init__.py
neural_de/transformations/diffusion/diffpure_config.py
neural_de/transformations/diffusion/diffusion_enhancer.py
neural_de/transformations/diffusion/rev_guided_diffusion.py
neural_de/transformations/diffusion/rev_vpsde.py
neural_de/transformations/diffusion/unet/__init__.py
neuralde.egg-info/PKG-INFO
neuralde.egg-info/SOURCES.txt
neuralde.egg-info/dependency_links.txt
neuralde.egg-info/entry_points.txt
neuralde.egg-info/requires.txt
neuralde.egg-info/top_level.txt