Metadata-Version: 2.4
Name: neuralde
Version: 1.1.0
Summary: Image enhancement library: corruption (noise, meteorological...), removal"
Author: IRT SystemX, Air Liquide
Author-email: contact@confiance.ai
License-Expression: MPL-2.0
Project-URL: Homepage, https://irt-systemx.github.io/neuralde/
Project-URL: Documentation, https://irt-systemx.github.io/neuralde/
Project-URL: Repository, https://github.com/IRT-SystemX/neuralde
Requires-Python: <3.11,>=3.9
License-File: LICENSE
Requires-Dist: pytest==7.4.2
Requires-Dist: numpy==1.24.3
Requires-Dist: torch==2.0.1
Requires-Dist: tensorflow==2.10.0
Requires-Dist: tensorflow-hub==0.14.0
Requires-Dist: einops==0.6.1
Requires-Dist: opencv-python==4.8.0.76
Requires-Dist: transformers==4.33.2
Requires-Dist: torchvision==0.15.2
Requires-Dist: imageio==2.31.6
Requires-Dist: sympy==1.12
Requires-Dist: scikit-image==0.21.0
Requires-Dist: lmdb==1.4.1
Requires-Dist: tqdm==4.65.2
Requires-Dist: requests==2.31.0
Requires-Dist: scipy==1.11.4
Requires-Dist: matplotlib==3.7.5
Requires-Dist: pillow==10.0.1
Requires-Dist: torchsde==0.2.6
Requires-Dist: six==1.16.0
Requires-Dist: attrs==23.1.0
Requires-Dist: albumentations==1.3.1
Requires-Dist: imagecorruptions==1.1.2
Requires-Dist: wheel==0.42.0
Requires-Dist: pyaml==25.1.0
Dynamic: license-file
